modo_data_science_helpers/__init__.py
modo_data_science_helpers/aws_utils.py
modo_data_science_helpers-0.5.3.dist-info/METADATA
modo_data_science_helpers-0.5.3.dist-info/WHEEL
modo_data_science_helpers-0.5.3.dist-info/RECORD
