Metadata-Version: 2.1
Name: modo-data-science-helpers
Version: 0.5.3
Summary: Helpers for AWS most common operations. Includes clipboard auth
Author: Esteban Elia
Author-email: esteban.elia@modo.com.ar
Requires-Python: >=3.7,<4.0
Classifier: Programming Language :: Python :: 3
Classifier: Programming Language :: Python :: 3.7
Classifier: Programming Language :: Python :: 3.8
Classifier: Programming Language :: Python :: 3.9
Classifier: Programming Language :: Python :: 3.10
Classifier: Programming Language :: Python :: 3.11
Requires-Dist: awswrangler (>=2.20.1,<3.0.0)
Requires-Dist: boto3 (>=1.26.111,<2.0.0)
Requires-Dist: clipboard (>=0.0.4,<0.0.5)
Requires-Dist: pandas (>=1.3.5,<2.0.0)
Requires-Dist: regex (>=2022.10.31,<2023.0.0)
